{
  "keywords": {
    "тіна кароль": {
      "last_seen_post_id": "3869195987579695108_71772992768",
      "first_seen_run_at": "2026-04-06T11:29:02.684106+00:00",
      "last_seen_run_at": "2026-04-06T11:29:02.684106+00:00",
      "mode": "recent"
    },
    "tina_karol": {
      "last_seen_post_id": "3869281704733500055_63431857564",
      "first_seen_run_at": "2026-04-06T11:29:16.684714+00:00",
      "last_seen_run_at": "2026-04-06T11:29:16.684714+00:00",
      "mode": "recent"
    },
    "тінакароль": {
      "last_seen_post_id": "3868037730009969326_78781725238",
      "first_seen_run_at": "2026-04-06T11:29:29.700505+00:00",
      "last_seen_run_at": "2026-04-06T11:29:29.700505+00:00",
      "mode": "recent"
    },
    "python": {
      "last_seen_post_id": "3889524903791836331_76289284779",
      "first_seen_run_at": "2026-05-04T09:41:50.404224+00:00",
      "last_seen_run_at": "2026-05-04T09:44:51.033686+00:00",
      "mode": "recent"
    },
    "azure": {
      "last_seen_post_id": "3889517295928155614_29901402559",
      "first_seen_run_at": "2026-05-04T09:46:19.324407+00:00",
      "last_seen_run_at": "2026-05-04T09:46:19.324407+00:00",
      "mode": "recent"
    },
    "тцк": {
      "last_seen_post_id": "3889562654583124412_63046734263",
      "first_seen_run_at": "2026-05-04T09:54:35.442146+00:00",
      "last_seen_run_at": "2026-05-04T10:54:44.971493+00:00",
      "mode": "recent"
    },
    "леді гага": {
      "last_seen_post_id": "3889550288433297373_63080366172",
      "first_seen_run_at": "2026-05-04T09:58:43.666747+00:00",
      "last_seen_run_at": "2026-05-04T10:47:30.364205+00:00",
      "mode": "recent"
    },
    "осадча": {
      "last_seen_post_id": "3891012519762626084_73472244645",
      "first_seen_run_at": "2026-05-04T11:11:30.852665+00:00",
      "last_seen_run_at": "2026-05-06T11:34:39.762197+00:00",
      "mode": "recent"
    },
    "Тцк": {
      "last_seen_post_id": "3889740758102072058_23351670141",
      "first_seen_run_at": "2026-05-04T16:49:40.826366+00:00",
      "last_seen_run_at": "2026-05-04T16:49:40.827338+00:00",
      "mode": "recent"
    }
  }
}